MANIFEST.in
setup.cfg
setup.py
yamlradio/__init__.py
yamlradio/fabriek.py
yamlradio/keypress.py
yamlradio/parser.py
yamlradio/radio.py
yamlradio/yamlradio.py
yamlradio/zenders.yml
yamlradio.egg-info/PKG-INFO
yamlradio.egg-info/SOURCES.txt
yamlradio.egg-info/dependency_links.txt
yamlradio.egg-info/entry_points.txt
yamlradio.egg-info/requires.txt
yamlradio.egg-info/top_level.txt
yamlradio/communicators/_3fm.py
yamlradio/communicators/_538.py
yamlradio/communicators/_538ib.py
yamlradio/communicators/__init__.py
yamlradio/communicators/default.py
yamlradio/communicators/hitfm.py