Metadata-Version: 1.0
Name: yamlradio
Version: 2.0.2
Summary: A small Python3 package to play radio stations as defined in a YAML file.
Home-page: https://github.com/GijsTimmers/yamlradio
Author: Gijs Timmers
Author-email: gijs.timmers@student.kuleuven.be
License: UNKNOWN
Keywords: radio,terminal,yaml
Platform: UNKNOWN
